setup.py
docs/History.rst
docs/Readme.rst
vinisto/__init__.py
vinisto/main.py
vinisto.egg-info/PKG-INFO
vinisto.egg-info/SOURCES.txt
vinisto.egg-info/dependency_links.txt
vinisto.egg-info/entry_points.txt
vinisto.egg-info/not-zip-safe
vinisto.egg-info/requires.txt
vinisto.egg-info/top_level.txt
vinisto/i18n/__init__.py
vinisto/i18n/es_ES/LC_MESSAGES/vinisto.mo
vinisto/i18n/es_ES/LC_MESSAGES/vinisto.po
vinisto/plugins/__init__.py
vinisto/plugins/gpio.py
vinisto/plugins/ir.py
vinisto/plugins/repeat.py
vinisto/plugins/time.py
vinisto/stt/__init__.py
vinisto/stt/google_stt.py
vinisto/tts/__init__.py
vinisto/tts/google_tts.py