Metadata-Version: 1.1
Name: vinisto
Version: 0.2.1
Summary: 
Home-page: https://github.com/XayOn/vinisto
Author: David Francos Cuartero
Author-email: me@davidfrancos.net
License: BSD
Keywords: vinisto
Platform: UNKNOWN
Classifier: Development Status :: 2 - Pre-Alpha
Classifier: Intended Audience :: Developers
Classifier: License :: OSI Approved :: BSD License
Classifier: Natural Language :: English
Classifier: Programming Language :: Python :: 3
Classifier: Programming Language :: Python :: 3.3
Classifier: Programming Language :: Python :: 3.4
